pythermonomics/__init__.py
pythermonomics/cli.py
pythermonomics/exceptions.py
pythermonomics/geothermal_economics.py
pythermonomics/config/__init__.py
pythermonomics/config/energy_loss_parameters.py
pythermonomics/config/geothermal_economics_config.py
pythermonomics/config/reservoir_simulation_parameters.py
pythermonomics/config/techno_economic_config.py
pythermonomics/config/well_trajectories_config.py
pythermonomics/data/__init__.py
pythermonomics/data/base_well_results.py
pythermonomics/data/read_deviation_file.py
pythermonomics/data/read_sim_data_from_csv.py
pythermonomics/data/simulation_model_results.py
pythermonomics/data/well_results.py
pythermonomics/energy_model/__init__.py
pythermonomics/energy_model/energy_calculator.py
pythermonomics/npv_model/__init__.py
pythermonomics/npv_model/costmodel_well.py
pythermonomics/npv_model/economics_calculator.py
pythermonomics/npv_model/unit_maps.py
pythermonomics-0.1.2.dist-info/licenses/LICENSE
pythermonomics-0.1.2.dist-info/METADATA
pythermonomics-0.1.2.dist-info/WHEEL
pythermonomics-0.1.2.dist-info/entry_points.txt
pythermonomics-0.1.2.dist-info/top_level.txt
pythermonomics-0.1.2.dist-info/RECORD
