Metadata-Version: 2.4
Name: pythermonomics
Version: 0.1.2
Summary: Tools for geothermal techno-economics, including NPV, LCOE, well simulation, and more.
Author-email: Stephan de Hoop <stephan.dehoop@tno.nl>
License:                     GNU GENERAL PUBLIC LICENSE
Project-URL: Homepage, https://github.com/TNO/pythermonomics
Project-URL: Repository, https://github.com/TNO/pythermonomics
Project-URL: Issues, https://github.com/TNO/pythermonomics/issues
Keywords: geothermal,energy,npv,lcoe,economics,techno-economics
Classifier: Programming Language :: Python :: 3
Classifier: Programming Language :: Python :: 3 :: Only
Classifier: Programming Language :: Python :: 3.11
Classifier: Programming Language :: Python :: 3.12
Classifier: License :: OSI Approved :: GNU General Public License v3 (GPLv3)
Classifier: Operating System :: OS Independent
Classifier: Intended Audience :: Science/Research
Classifier: Topic :: Scientific/Engineering
Requires-Python: >=3.11
License-File: LICENSE
Requires-Dist: numpy_financial
Requires-Dist: numpy
Requires-Dist: pandas
Requires-Dist: pydantic
Requires-Dist: pyyaml
Requires-Dist: pywellgeo
Provides-Extra: docs
Requires-Dist: mkdocs; extra == "docs"
Requires-Dist: mkdocstrings[python]; extra == "docs"
Requires-Dist: mkdocs-material; extra == "docs"
Requires-Dist: mike; extra == "docs"
Provides-Extra: tests
Requires-Dist: pytest; extra == "tests"
Provides-Extra: notebook
Requires-Dist: notebook>=7; extra == "notebook"
Requires-Dist: jupyterlab>=4; extra == "notebook"
Requires-Dist: ipykernel>=6; extra == "notebook"
Requires-Dist: ipywidgets>=8; extra == "notebook"
Requires-Dist: matplotlib>=3.8; extra == "notebook"
Requires-Dist: plotly>=5.20; extra == "notebook"
Dynamic: license-file
